Metadata-Version: 2.4
Name: django-crud-sundae
Version: 0.1.0
Summary: A useful view class for creating CRUD views in Django (With Tailwind & HTMX & extensible plugin system)
Home-page: https://github.com/leonh/django-crud-sundae
Author: Leon Harris
Author-email: 
License-Expression: MIT
Project-URL: Homepage, https://github.com/leonh/django-crud-sundae
Project-URL: Source, https://github.com/leonh/django-crud-sundae
Project-URL: Tracker, https://github.com/leonh/django-crud-sundae/issues
Keywords: django,crud,views,htmx,tailwind
Classifier: Development Status :: 3 - Alpha
Classifier: Environment :: Web Environment
Classifier: Framework :: Django
Classifier: Framework :: Django :: 3.2
Classifier: Framework :: Django :: 4.0
Classifier: Framework :: Django :: 4.1
Classifier: Framework :: Django :: 4.2
Classifier: Framework :: Django :: 5.0
Classifier: Intended Audience :: Developers
Classifier: Operating System :: OS Independent
Classifier: Programming Language :: Python
Classifier: Programming Language :: Python :: 3
Classifier: Programming Language :: Python :: 3.8
Classifier: Programming Language :: Python :: 3.9
Classifier: Programming Language :: Python :: 3.10
Classifier: Programming Language :: Python :: 3.11
Classifier: Programming Language :: Python :: 3.12
Classifier: Topic :: Internet :: WWW/HTTP
Classifier: Topic :: Internet :: WWW/HTTP :: Dynamic Content
Requires-Python: >=3.8
License-File: LICENSE
Requires-Dist: Django>=3.2
Dynamic: home-page
Dynamic: license-file
Dynamic: requires-python
